{
  "timestamp": "20251214_114242",
  "event_type": "event.data.epoch.create",
  "end_user_id": "a9bdec856974e93648c6674ac706c9dd",
  "content_encoding": "zstd",
  "raw_body_size": 254,
  "headers": {
    "host": "api.yourhealth1place.eu",
    "x-real-ip": "80.158.109.167",
    "x-forwarded-for": "80.158.109.167",
    "x-forwarded-proto": "https",
    "connection": "upgrade",
    "content-length": "340",
    "accept": "text/plain, application/json, application/yaml, application/*+json, */*",
    "content-type": "application/json",
    "x-hmac-signature": "74609207e97c0008d6af38116ef7514f4bf09f40f9d5a3a9a03aaaed79154dce",
    "x-hmac-timestamp": "1765712561556",
    "x-hmac-algorithm": "hmac-sha256",
    "content-encoding": "zstd",
    "traceparent": "00-e515408836d620f27a8f202ee45246fd-9ddc397c15204e43-01",
    "accept-encoding": "gzip, x-gzip, deflate",
    "user-agent": "Apache-HttpClient/5.4.3 (Java/21.0.9)"
  },
  "saved_at": "2025-12-14T11:42:42.204010"
}